Workbook

Sheet Instructions
A1: The Company — Credit Progress Audit Working Kit
A2: Prepared by Henry C. Dibie, Credit Risk Analyst | Reference: FY2025 Baseline → FY2026 Update
A4: HOW TO USE THIS FILE
A5: Step | B5: Sheet | C5: Action | D5: Who
A6: 1 | B6: Data Entry | C6: Enter the FY2026 financial figures (Balance Sheet + P&L) in the BLUE cells. All other cells will update automatically. | D6: Client
A7: 2 | B7: Ratio Calculator | C7: Review all ratios — they are auto-calculated from your entries. No manual input needed here. | D7: Client
A8: 3 | B8: Progress Tracker | C8: Review the Before vs After comparison. The Movement column updates automatically once FY2026 data is entered. | D8: Client
A9: 4 | B9: Recommendation Checklist | C9: Select the status (Completed / In Progress / Not Started) for each of the 11 recommendations using the dropdown. | D9: Client
A10: 5 | B10: All Sheets | C10: Save the file and share with Henry for the final narrative update, or use the pre-written scenario text in column F of the Progress Tracker. | D10: Client
A12: COLOUR KEY
A13: Sample | B13: Blue text on light blue background = INPUT CELL. Enter your figures here.
A14: Sample | B14: Black text on white background = FORMULA. Auto-calculated. Do not edit.
A15: Sample | B15: Green background = Improvement vs baseline (good direction).
A16: Sample | B16: Amber background = No change / marginal movement.
A17: Sample | B17: Red background = Deterioration vs baseline (needs attention).
A18: Sample | B18: Yellow background = Key assumption cell requiring attention.

Sheet Data Entry
A1: STEP 1 — Enter FY2026 Financial Data Here
A2: Enter figures in SGD. Blue cells only. All other sheets update automatically.
A4: Line Item | B4: FY2025 Baseline (Original Report) | C4: FY2026 Actual (Enter Here) | D4: Notes / Source
A5: BALANCE SHEET — As at 28 February 2026
A6: CURRENT ASSETS
A7: Cash and Cash Equivalents | B7: 14588105 | D7: From bank statements / audited accounts
A8: Trade Receivables | D8: Gross amount before any provisions
A9: Other Current Assets | D9: Contract assets, prepayments, deposits
A10: TOTAL CURRENT ASSETS | B10: 59122413 | D10: Sum of all current assets above
A11: CURRENT LIABILITIES
A12: Trade Payables | D12: Amounts owed to suppliers
A13: Contract Liabilities | D13: Advance billings / progress billings received
A14: Other Current Liabilities | D14: Accruals, tax payable, other short-term
A15: TOTAL CURRENT LIABILITIES | B15: 46217149 | D15: Sum of all current liabilities above
A16: NON-CURRENT LIABILITIES
A17: Bank Borrowings (Long-Term) | D17: Term loans, hire purchase > 12 months
A18: Other Non-Current Liabilities | D18: Deferred tax, provisions, etc.
A19: TOTAL LIABILITIES | B19: 46381083 | D19: Current + Non-current liabilities
A20: SHAREHOLDERS' EQUITY (NET WORTH) | B20: 17113302 | D20: Total Assets minus Total Liabilities
A21: TOTAL ASSETS | B21: 63494385 | D21: Total Liabilities + Equity
A23: INCOME STATEMENT — Year Ending 28 February 2026
A24: Revenue (Total Turnover) | B24: 141123520 | D24: From audited accounts or management accounts
A25: Cost of Sales | B25: 128380066 | D25: Direct project costs
A26: Gross Profit | B26: 12743454 | D26: Revenue minus Cost of Sales
A27: Operating Expenses (Overheads) | D27: Admin, staff, depreciation (excl. finance costs)
A28: EBIT (Earnings Before Interest & Tax) | D28: Gross Profit minus Operating Expenses
A29: Finance Costs (Interest Expense) | D29: Bank interest and finance charges
A30: Net Profit After Tax | B30: 5692536 | D30: Bottom line from P&L
A32: ADDITIONAL DATA — Required for Ratio Calculations
A33: Trade Receivables (Closing Balance) | B33: — | D33: From Balance Sheet — used for collection period
A34: Trade Payables (Closing Balance) | B34: — | D34: From Balance Sheet — used for payment period
A35: SCCB Payment Rating (Updated) | B35: — | D35: From updated SCCB Comprehensive Report (out of 100)
A36: No. of Slow-Pay Markers (SCCB) | B36: — | D36: Count of slow/late payment entries in updated SCCB
A37: Days Beyond Terms / DBT (SCCB) | B37: — | D37: From updated SCCB report — average days beyond agreed terms

Sheet Ratio Calculator
A1: STEP 2 — Ratio Calculator (Auto-Updates from Data Entry Sheet)
A2: All ratios are calculated automatically. Each section shows the formula, what it measures, and how to interpret the result.
A4: Ratio Name | B4: Formula | C4: How to Calculate | D4: FY2025 Baseline | E4: FY2026 Result | F4: Target | G4: Interpretation
A5: 1. LIQUIDITY RATIOS — Can the Company pay its short-term debts?
A6: Current Ratio | B6: Current Assets ÷ Current Liabilities | C6: Shows whether the Company has enough short-term assets to cover its short-term debts. A ratio above 1.0x means assets exceed liabilities. Target for SCCB improvement: ≥1.50x. | D6: 1.28x | E6: =IFERROR('Data Entry'!C10/'Data Entry'!C15,"Enter data") | F6: ≥ 1.50x | G6: Below 1.0x = high risk. 1.0x–1.5x = moderate. Above 1.5x = healthy. The Company must reduce current liabilities (trade payables) to move this upward.
A7: Quick Ratio (Acid Test) | B7: (Current Assets − Inventory) ÷ Current Liabilities | C7: A stricter version of the current ratio that excludes inventory. Since The Company has minimal inventory (construction company), this closely mirrors the current ratio. | D7: 1.28x | E7: =IFERROR('Data Entry'!C10/'Data Entry'!C15,"Enter data") | F7: ≥ 1.50x | G7: For construction companies, quick ratio ≈ current ratio since inventory is minimal. Same interpretation applies.
A8: Cash Ratio | B8: Cash ÷ Current Liabilities | C8: The most conservative liquidity measure — shows how much of short-term debt could be paid with cash on hand right now. | D8: 0.32x | E8: =IFERROR('Data Entry'!C7/'Data Entry'!C15,"Enter data") | F8: ≥ 0.30x | G8: A ratio of 0.30x means the Company can cover 30% of its current liabilities with cash alone. Not expected to be high for a project-based business.
A9: Working Capital (SGD) | B9: Current Assets − Current Liabilities | C9: The absolute dollar buffer the Company has after paying all short-term debts. Positive = solvent. Growing working capital signals improving financial health. | D9: SGD 12,905,264 | E9: =IFERROR('Data Entry'!C10-'Data Entry'!C15,"Enter data") | F9: Growth vs FY2025 | G9: FY2025 working capital was SGD 12.9M. An increase signals the Company is accumulating financial strength.
A11: 2. LEVERAGE RATIOS — How much does the Company rely on debt?
A12: Total Debt to Equity (D/E) | B12: Total Liabilities ÷ Shareholders' Equity × 100 | C12: Shows what percentage of the Company's financing comes from debt vs. owner funds. High D/E means more reliance on debt, which increases credit risk. | D12: 271.02% | E12: =IFERROR('Data Entry'!C19/'Data Entry'!C20,"Enter data") | F12: Below 200% | G12: FY2025 D/E of 271% was driven by large trade payables from two major projects. As payables settle, this should fall. Target: below 200% to signal lower risk to SCCB.
A13: Total Debt to Assets (D/A) | B13: Total Liabilities ÷ Total Assets × 100 | C13: Shows what proportion of the Company's assets are financed by debt. A lower ratio means more of the Company's assets are owned outright. | D13: 73.05% | E13: =IFERROR('Data Entry'!C19/'Data Entry'!C21,"Enter data") | F13: Below 60% | G13: 73% means debt finances 73 cents of every dollar of assets. Target: below 60%, achievable as trade payables unwind.
A14: Interest Coverage Ratio | B14: EBIT ÷ Finance Costs (Interest) | C14: Shows how many times the Company can pay its interest from operating profit. Higher = safer. SCCB weights this heavily for construction companies. | D14: 160.82x | E14: =IFERROR('Data Entry'!C28/'Data Entry'!C29,"Enter data") | F14: Maintain > 10x | G14: FY2025 coverage of 160x was exceptionally strong. Any result above 10x is considered safe by lenders. Maintain this level.
A16: 3. PROFITABILITY RATIOS — Is the Company making money efficiently?
A17: Gross Profit Margin | B17: Gross Profit ÷ Revenue × 100 | C17: Shows what percentage of revenue remains after paying direct project costs. Construction sector median is approximately 8–10%. | D17: 9.03% | E17: =IFERROR(('Data Entry'!C24-'Data Entry'!C25)/'Data Entry'!C24,"Enter data") | F17: Maintain ≥ 8% | G17: FY2025 gross margin of 9.03% was above the sector median. Maintaining this level signals disciplined project cost management.
A18: Net Profit Margin | B18: Net Profit After Tax ÷ Revenue × 100 | C18: The bottom-line percentage — what the Company keeps from each dollar of revenue after all costs, interest, and tax. | D18: 4.03% | E18: =IFERROR('Data Entry'!C30/'Data Entry'!C24,"Enter data") | F18: Maintain ≥ 4% | G18: FY2025 net margin was 4.03%. Even a small margin on SGD 141M revenue generates significant profit. Lenders look for this to be positive and stable.
A19: Return on Assets (ROA) | B19: Net Profit After Tax ÷ Total Assets × 100 | C19: Measures how efficiently the Company uses its assets to generate profit. Above the sector median signals effective asset utilisation. | D19: 8.97% | E19: =IFERROR('Data Entry'!C30/'Data Entry'!C21,"Enter data") | F19: Maintain > 5% | G19: FY2025 ROA of 8.97% was well above the SCCB sector median of ~5%. Maintain above 5% to support the Financial Condition rating.
A20: Return on Equity (ROE) | B20: Net Profit After Tax ÷ Shareholders' Equity × 100 | C20: Shows how much profit the Company generates per dollar of owner equity. High ROE signals strong returns for shareholders. | D20: 33.26% | E20: =IFERROR('Data Entry'!C30/'Data Entry'!C20,"Enter data") | F20: Maintain > 10% | G20: FY2025 ROE of 33.26% was exceptionally high, partly due to the large leverage base. As D/E improves, ROE will moderate — this is expected and healthy.
A22: 4. EFFICIENCY RATIOS — How fast does the Company collect and pay?
A23: Collection Period (Days) | B23: (Trade Receivables ÷ Revenue) × 365 | C23: How many days on average it takes for the Company to collect payment from its customers after completing work. Lower = faster collection. | D23: 47.20 days | E23: =IFERROR(('Data Entry'!C33/'Data Entry'!C24)*365,"Enter data") | F23: Below 60 days | G23: FY2025 collection period of 47 days was a strong improvement from 68 days in FY2024. Maintaining below 60 days is the target.
A24: Payment Period (Days) | B24: (Trade Payables ÷ Cost of Sales) × 365 | C24: How many days on average the Company takes to pay its own suppliers. This is the MOST IMPORTANT ratio for SCCB payment score improvement. | D24: 80.84 days | E24: =IFERROR(('Data Entry'!C34/'Data Entry'!C25)*365,"Enter data") | F24: Below 60 days | G24: CRITICAL: At 80.84 days, the Company is paying suppliers nearly 3 months after receiving goods/services. Reducing this directly improves the SCCB payment score. Target: below 60 days.
A25: Asset Turnover | B25: Revenue ÷ Total Assets | C25: How efficiently the Company uses its assets to generate revenue. A ratio of 2.0x means every SGD 1 of assets generates SGD 2 of revenue. | D25: 2.22x | E25: =IFERROR('Data Entry'!C24/'Data Entry'!C21,"Enter data") | F25: Maintain > 1.5x | G25: FY2025 asset turnover of 2.22x was above the sector median of 1.08x. This reflects the Company's ability to generate high revenue from its asset base.

Sheet Progress Tracker
A1: STEP 3 — Credit Progress Tracker (Before vs After)
A2: FY2026 column auto-updates from Data Entry. Movement column shows direction of change. Use Scenario column for final narrative.
A4: Metric | B4: FY2025 Baseline | C4: FY2026 Result | D4: Movement | E4: Target | F4: Met? | G4: Scenario Narrative (Copy-Paste to Report)
A5: Current Ratio | B5: 1.28x | C5: =IFERROR('Ratio Calculator'!E6,"Pending") | D5: =IFERROR(IF('Ratio Calculator'!E6="Pending","—",IF('Ratio Calculator'!E6>=1.5,"▲ Improved",IF('Ratio Calculator'!E6>=1.5*0.95,"→ Marginal","▼ Declined"))),"—") | E5: ≥ 1.50x | F5: =IFERROR(IF('Ratio Calculator'!E6="Pending","—",IF('Ratio Calculator'!E6>=1.5,"✓ YES","✗ NO")),"—") | G5: ▲ GOOD: The current ratio has improved to [X]x, exceeding the 1.50x target. This directly supports the CA2 rating objective. → NEUTRAL: The current ratio has held broadly stable at [X]x. Continued trade payable reduction is required to reach the 1.50x target. ▼ CONCERN: The current ratio has declined to [X]x. Immediate action on trade payable settlement is required.
A6: Payment Period | B6: 80.84 days | C6: =IFERROR('Ratio Calculator'!E24,"Pending") | D6: =IFERROR(IF('Ratio Calculator'!E24="Pending","—",IF('Ratio Calculator'!E24<=60,"▲ Improved",IF('Ratio Calculator'!E24<=60*1.05,"→ Marginal","▼ Declined"))),"—") | E6: < 60 days | F6: =IFERROR(IF('Ratio Calculator'!E24="Pending","—",IF('Ratio Calculator'!E24<=60,"✓ YES","✗ NO")),"—") | G6: ▲ GOOD: The payment period has reduced to [X] days, below the 60-day target. This is the most impactful improvement for the SCCB payment score. → NEUTRAL: The payment period remains above 60 days at [X] days. Focused supplier payment prioritisation is required. ▼ CONCERN: The payment period has increased to [X] days. This will negatively affect the SCCB payment rating and requires immediate intervention.
A7: Total Debt to Equity | B7: 271.02% | C7: =IFERROR('Ratio Calculator'!E12,"Pending") | D7: =IFERROR(IF('Ratio Calculator'!E12="Pending","—",IF('Ratio Calculator'!E12<=200,"▲ Improved",IF('Ratio Calculator'!E12<=200*1.05,"→ Marginal","▼ Declined"))),"—") | E7: < 200% | F7: =IFERROR(IF('Ratio Calculator'!E12="Pending","—",IF('Ratio Calculator'!E12<=200,"✓ YES","✗ NO")),"—") | G7: ▲ GOOD: Debt-to-equity has reduced to [X]%, below the 200% target. This signals materially lower financial risk to SCCB. → NEUTRAL: Debt-to-equity remains elevated at [X]%. Trade payable settlement is the primary lever to reduce this ratio. ▼ CONCERN: Debt-to-equity has increased to [X]%. This indicates the Company's debt burden has grown relative to its equity base.
A8: Net Profit Margin | B8: 4.03% | C8: =IFERROR('Ratio Calculator'!E18,"Pending") | D8: =IFERROR(IF('Ratio Calculator'!E18="Pending","—",IF('Ratio Calculator'!E18>=0.04,"▲ Improved",IF('Ratio Calculator'!E18>=0.04*0.95,"→ Marginal","▼ Declined"))),"—") | E8: ≥ 4.0% | F8: =IFERROR(IF('Ratio Calculator'!E18="Pending","—",IF('Ratio Calculator'!E18>=0.04,"✓ YES","✗ NO")),"—") | G8: ▲ GOOD: Net margin has been maintained at [X]%, demonstrating sustained profitability as the major FY2025 projects mature. → NEUTRAL: Net margin has moderated to [X]%, which is within the acceptable range for the sector. ▼ CONCERN: Net margin has declined to [X]%. If below 2%, this may signal margin compression on large projects requiring management attention.
A9: SCCB Payment Rating | B9: 59/100 | C9: =IFERROR('Data Entry'!C35,"Pending") | D9: =IFERROR(IF('Data Entry'!C35="Pending","—",IF('Data Entry'!C35>=70,"▲ Improved",IF('Data Entry'!C35>=70*0.95,"→ Marginal","▼ Declined"))),"—") | E9: ≥ 70/100 | F9: =IFERROR(IF('Data Entry'!C35="Pending","—",IF('Data Entry'!C35>=70,"✓ YES","✗ NO")),"—") | G9: ▲ GOOD: The SCCB payment rating has improved to [X]/100, above the 70-point threshold. This is consistent with a CA2 rating trajectory. → NEUTRAL: The SCCB payment rating has improved marginally to [X]/100. Continued payment discipline is required to reach the 70+ threshold. ▼ CONCERN: The SCCB payment rating has declined to [X]/100. Urgent action on slow-pay entries and supplier settlements is required.
A10: Collection Period | B10: 47.20 days | C10: =IFERROR('Ratio Calculator'!E23,"Pending") | D10: =IFERROR(IF('Ratio Calculator'!E23="Pending","—",IF('Ratio Calculator'!E23<=60,"▲ Improved",IF('Ratio Calculator'!E23<=60*1.05,"→ Marginal","▼ Declined"))),"—") | E10: < 60 days | F10: =IFERROR(IF('Ratio Calculator'!E23="Pending","—",IF('Ratio Calculator'!E23<=60,"✓ YES","✗ NO")),"—") | G10: ▲ GOOD: The collection period has been maintained at [X] days, below the 60-day threshold. Cash conversion from project completions remains efficient. → NEUTRAL: The collection period has extended to [X] days. Monitor closely, particularly as projects approach completion milestones. ▼ CONCERN: The collection period has exceeded 60 days at [X] days. Review milestone billing processes and follow up on outstanding receivables.
A11: Return on Assets | B11: 8.97% | C11: =IFERROR('Ratio Calculator'!E19,"Pending") | D11: =IFERROR(IF('Ratio Calculator'!E19="Pending","—",IF('Ratio Calculator'!E19>=0.05,"▲ Improved",IF('Ratio Calculator'!E19>=0.05*0.95,"→ Marginal","▼ Declined"))),"—") | E11: > 5.0% | F11: =IFERROR(IF('Ratio Calculator'!E19="Pending","—",IF('Ratio Calculator'!E19>=0.05,"✓ YES","✗ NO")),"—") | G11: ▲ GOOD: ROA has been maintained at [X]%, above the sector median of ~5%. Asset utilisation remains strong. → NEUTRAL: ROA has moderated to [X]%. This is within normal range as project mix and asset base evolve. ▼ CONCERN: ROA has declined below 5% to [X]%. Review asset efficiency and consider whether the asset base is appropriately sized for current revenue.

Sheet Recommendation Checklist
A1: STEP 4 — Recommendation Implementation Checklist
A2: Use the dropdown in the Status column to mark each recommendation. Add evidence/notes in the last column.
A4: # | B4: Timeframe | C4: Recommendation | D4: Status | E4: Credit Impact | F4: Evidence / Notes
A5: 1 | B5: IMMEDIATE (0–30 Days) | C5: Set up AP ageing tracker and payment priority list | D5: Not Started | E5: Targets SCCB payment rating from 59 toward 70+/100
A6: 2 | B6: IMMEDIATE (0–30 Days) | C6: Initiate discussions with a relationship bank on revolving credit facility (SGD 5–10M) | D6: Not Started | E6: Enables current ratio recovery toward 1.50x target
A7: 3 | B7: IMMEDIATE (0–30 Days) | C7: Compile contract register and revenue backlog documentation | D7: Not Started | E7: Required for a relationship bank facility application; supports Financial Condition rating
A8: 4 | B8: IMMEDIATE (0–30 Days) | C8: Verify ACRA and SCCB records for all director and company records in bureau files | D8: Not Started | E8: Removes potential data discrepancies suppressing the credit rating
A9: 5 | B9: IMMEDIATE (0–30 Days) | C9: Identify SCCB-reporting trade creditors and flag for priority payment | D9: Not Started | E9: Zero-cost action with direct payment score impact
A10: 6 | B10: SHORT-TERM (1–3 Months) | C10: Settle top 5 largest overdue supplier payments | D10: Not Started | E10: Directly improves SCCB payment score toward 70+ threshold
A11: 7 | B11: SHORT-TERM (1–3 Months) | C11: Submit revolving credit facility application to a relationship bank | D11: Not Started | E11: Targets current ratio above 1.50x; reduces concentration of current liabilities
A12: 8 | B12: SHORT-TERM (1–3 Months) | C12: Sign formal contra/offset agreements with related-party entities | D12: Not Started | E12: Clarifies inter-company netting in SCCB payment data; supports dispute submissions
A13: 9 | B13: SHORT-TERM (1–3 Months) | C13: Begin producing monthly management accounts from March 2026 | D13: Not Started | E13: Institutional lender readiness; governance improvement
A14: 10 | B14: MEDIUM-TERM (3–6 Months) | C14: Review payment terms with top 10 suppliers; align with project cash inflows | D14: Not Started | E14: Structural fix for payment period; targets reduction from 80.84 days to below 60 days
A15: 11 | B15: MEDIUM-TERM (3–6 Months) | C15: Commission FY2026 audit with an accredited audit firm; prepare three-year projections | D15: Not Started | E15: Required for institutional facility applications above SGD 5M; supports CA2 application
A16: SUMMARY | D16: =COUNTIF(D5:D15,"Completed") | E16: =COUNTIF(D5:D15,"In Progress") | F16: =COUNTIF(D5:D15,"Not Started")
